CHANGES.rst
LICENSE.txt
MANIFEST.in
README.rst
setup.py
django_jsdir.egg-info/PKG-INFO
django_jsdir.egg-info/SOURCES.txt
django_jsdir.egg-info/dependency_links.txt
django_jsdir.egg-info/requires.txt
django_jsdir.egg-info/top_level.txt
django_jsdir.egg-info/zip-safe
jsdir/__init__.py
jsdir/core.py
jsdir/jinja2.py
jsdir/models.py
jsdir/version.py
jsdir/management/__init__.py
jsdir/management/commands/__init__.py
jsdir/management/commands/collectstatic.py
jsdir/management/commands/runserver.py
jsdir/management/commands/test.py
jsdir/templatetags/__init__.py
jsdir/templatetags/jsdir.py