Metadata-Version: 1.1
Name: django-jsdir
Version: 0.2
Summary: Eases the management of JS files in a django app
Home-page: https://bitbucket.org/tkhyn/django-jsdir/
Author: Thomas Khyn
Author-email: thomas@ksytek.com
License: UNKNOWN
Keywords: js,javascript,directory,concatenate
Platform: UNKNOWN
Classifier: Programming Language :: Python
Classifier: Programming Language :: Python :: 2.7
Classifier: License :: OSI Approved :: MIT License
Classifier: Operating System :: OS Independent
Classifier: Development Status :: 5 - Production/Stable
Classifier: Intended Audience :: Developers
Classifier: Framework :: Django
Classifier: Environment :: Plugins
Classifier: Topic :: Software Development :: Build Tools
Classifier: Topic :: Text Processing
Classifier: Topic :: Software Development :: Libraries :: Python Modules
Classifier: Topic :: Utilities
